kebiml/__init__.py
kebiml/notebooks/multiclass_decision_boundary.ipynb
kebiml/visutil/decision_boundary.py
kebiml-0.0.2.dist-info/METADATA
kebiml-0.0.2.dist-info/WHEEL
kebiml-0.0.2.dist-info/licenses/LICENSE
kebiml-0.0.2.dist-info/RECORD
