Metadata-Version: 2.1
Name: kebiml
Version: 0.0.2
Summary: A simple private ml utilities
Project-URL: Homepage, https://github.com/freeislet/kebiml
Project-URL: Bug Tracker, https://github.com/freeislet/kebiml/issues
Author-email: Sunghwan Kang <freeislet@gmail.com>
License-File: LICENSE
Classifier: License :: OSI Approved :: MIT License
Classifier: Operating System :: OS Independent
Classifier: Programming Language :: Python :: 3
Requires-Python: >=3.8
Requires-Dist: matplotlib~=3.7
Requires-Dist: numpy~=1.21
Requires-Dist: scikit-learn~=1.3.2
